{
  "name": "Пирог \"Белорусский\"",
  "id": 200,
  "announce": [
    "Пирог для любителей сухого, рассыпчатого песочного теста и вкусной творожной начинки с орехами и изюмом."
  ],
  "description": [
    ""
  ],
  "ingredients": [
    {
      "name": "Для теста:",
      "count": ""
    },
    {
      "name": "Мука – 3,5 стакана",
      "count": ""
    },
    {
      "name": "Сахар – 1 стакан",
      "count": ""
    },
    {
      "name": "Маргарин холодный – 200 г",
      "count": ""
    },
    {
      "name": "Для начинки:",
      "count": ""
    },
    {
      "name": "Творог – 0,5 кг",
      "count": ""
    },
    {
      "name": "Яйца – 2 шт.",
      "count": ""
    },
    {
      "name": "Сахар – 1 стакан",
      "count": ""
    },
    {
      "name": "Орехи чищенные – 1 стакан",
      "count": ""
    },
    {
      "name": "Изюм – 1 стакан",
      "count": ""
    },
    {
      "name": "Ваниль – 1 пакетик",
      "count": ""
    }
  ],
  "steps": [
    "Ингредиенты для песочного пирога с творогом.",
    "Как приготовить песочный пирог с творогом: Для теста тертый маргарин, сахар и муку перемешиваем и растираем до сыпучей крошки.",
    "Запариваем изюм, потом воду сливаем, а изюм сушим салфеткой. Орехи измельчаем до крупной крошки (блендером). С помощью миксера смешиваем творог, яйца, сахар, ваниль и орехи. Потом подмешиваем изюм.",
    "2/3 общей массы теста высыпаем в разъемную форму, делаем бортики, выкладываем всю начинку.",
    "На начинку – остальную часть теста. Разравниваем лопаткой. Ставим в разогретую до 180-190 градусов духовку на 1 час. Остывший песочный пирог с творогом на 1-2 часа поставить в холодильник, а потом порезать на кусочки.",
    "Готовый песочный пирог с творогом. Приятного аппетита!"
  ]
}